{
  "average_frame_build_time_millis": 1.215,
  "90th_percentile_frame_build_time_millis": 2.233,
  "99th_percentile_frame_build_time_millis": 7.877,
  "worst_frame_build_time_millis": 30.449,
  "missed_frame_build_budget_count": 6,
  "average_frame_rasterizer_time_millis": 3.256,
  "90th_percentile_frame_rasterizer_time_millis": 4.169,
  "99th_percentile_frame_rasterizer_time_millis": 8.233,
  "worst_frame_rasterizer_time_millis": 38.174,
  "average_layer_cache_count": 0.0,
  "90th_percentile_layer_cache_count": 0,
  "99th_percentile_layer_cache_count": 0,
  "worst_layer_cache_count": 0,
  "average_layer_cache_memory": 0.0,
  "90th_percentile_layer_cache_memory": 0.0,
  "99th_percentile_layer_cache_memory": 0.0,
  "worst_layer_cache_memory": 0.0,
  "average_picture_cache_count": 0.0,
  "90th_percentile_picture_cache_count": 0,
  "99th_percentile_picture_cache_count": 0,
  "worst_picture_cache_count": 0,
  "average_picture_cache_memory": 0.0,
  "90th_percentile_picture_cache_memory": 0.0,
  "99th_percentile_picture_cache_memory": 0.0,
  "worst_picture_cache_memory": 0.0,
  "missed_frame_rasterizer_budget_count": 2,
  "frame_count": 1240,
  "frame_build_times": [
    7877,
    4996,
    2638,
    2098,
    1878,
    2183,
    2017,
    2137,
    1537,
    1922,
    1787,
    1958,
    1658,
    1452,
    381,
    332,
    489,
    419,
    415,
    349,
    362,
    582,
    261,
    570,
    941,
    381,
    545,
    503,
    571,
    682,
    398,
    480,
    715,
    671,
    509,
    1177,
    484,
    307,
    366,
    545,
    487,
    426,
    516,
    676,
    756,
    399,
    492,
    461,
    746,
    290,
    585,
    414,
    476,
    293,
    500,
    392,
    407,
    643,
    401,
    719,
    616,
    303,
    530,
    497,
    530,
    454,
    584,
    664,
    1048,
    574,
    531,
    601,
    413,
    616,
    522,
    399,
    493,
    647,
    325,
    365,
    564,
    524,
    475,
    598,
    713,
    589,
    660,
    308,
    460,
    806,
    332,
    404,
    651,
    658,
    386,
    557,
    432,
    540,
    709,
    559,
    410,
    938,
    431,
    825,
    326,
    413,
    285,
    1236,
    715,
    875,
    382,
    613,
    440,
    395,
    543,
    456,
    494,
    435,
    631,
    591,
    1003,
    463,
    368,
    428,
    525,
    374,
    405,
    1054,
    449,
    777,
    548,
    433,
    669,
    722,
    610,
    930,
    396,
    1031,
    441,
    360,
    440,
    841,
    312,
    291,
    660,
    489,
    1559,
    661,
    477,
    722,
    601,
    509,
    805,
    861,
    482,
    351,
    481,
    462,
    446,
    532,
    382,
    410,
    352,
    612,
    608,
    303,
    659,
    454,
    492,
    446,
    496,
    1651,
    358,
    596,
    476,
    614,
    590,
    438,
    488,
    774,
    795,
    1125,
    490,
    762,
    587,
    454,
    481,
    1055,
    676,
    318,
    649,
    849,
    1285,
    408,
    1153,
    638,
    588,
    462,
    258,
    389,
    713,
    527,
    496,
    671,
    699,
    536,
    470,
    637,
    1234,
    313,
    375,
    347,
    880,
    301,
    599,
    544,
    482,
    471,
    318,
    480,
    529,
    430,
    362,
    379,
    342,
    400,
    336,
    409,
    501,
    220,
    165,
    543,
    371,
    518,
    319,
    324,
    386,
    416,
    536,
    577,
    528,
    496,
    857,
    676,
    668,
    517,
    503,
    307,
    439,
    377,
    532,
    520,
    503,
    443,
    609,
    1052,
    571,
    821,
    417,
    1119,
    435,
    397,
    325,
    565,
    443,
    552,
    319,
    391,
    498,
    571,
    1309,
    7770,
    4608,
    1439,
    1570,
    2178,
    2876,
    1668,
    3160,
    2288,
    1906,
    1695,
    1687,
    1304,
    2406,
    2015,
    2218,
    1690,
    588,
    388,
    434,
    417,
    413,
    409,
    387,
    595,
    576,
    726,
    280,
    578,
    565,
    522,
    476,
    270,
    471,
    511,
    630,
    636,
    570,
    607,
    790,
    521,
    526,
    864,
    1007,
    537,
    268,
    656,
    1042,
    523,
    545,
    554,
    562,
    620,
    487,
    443,
    230,
    737,
    538,
    581,
    822,
    729,
    514,
    592,
    491,
    751,
    612,
    998,
    599,
    690,
    843,
    567,
    507,
    462,
    750,
    584,
    699,
    454,
    670,
    384,
    628,
    436,
    497,
    437,
    430,
    488,
    1013,
    380,
    605,
    275,
    960,
    835,
    293,
    2996,
    751,
    1299,
    1422,
    964,
    677,
    1155,
    1138,
    1378,
    1047,
    1511,
    1372,
    1610,
    898,
    1167,
    1304,
    1226,
    1604,
    2384,
    1453,
    1715,
    2742,
    1987,
    1696,
    2065,
    2439,
    1902,
    2703,
    2405,
    3747,
    2820,
    2387,
    2073,
    2069,
    2597,
    2886,
    2996,
    1715,
    2380,
    2798,
    1929,
    2333,
    1568,
    1322,
    486,
    770,
    669,
    1568,
    522,
    1404,
    932,
    1474,
    860,
    1132,
    985,
    1179,
    1152,
    1971,
    1758,
    1592,
    2159,
    1477,
    1556,
    1344,
    2188,
    2312,
    1649,
    1392,
    2730,
    2448,
    879,
    1681,
    2053,
    930,
    1718,
    2547,
    1987,
    1825,
    1285,
    2130,
    1756,
    1078,
    3712,
    1848,
    1386,
    1108,
    2519,
    1895,
    1289,
    1107,
    1698,
    845,
    1417,
    990,
    940,
    1430,
    1536,
    1042,
    1528,
    773,
    827,
    873,
    1501,
    1669,
    1810,
    1279,
    1934,
    1137,
    1149,
    2593,
    2085,
    1209,
    9033,
    4263,
    3569,
    856,
    587,
    655,
    706,
    455,
    455,
    680,
    866,
    735,
    960,
    709,
    521,
    771,
    639,
    904,
    619,
    892,
    656,
    767,
    743,
    829,
    599,
    600,
    667,
    662,
    709,
    2246,
    568,
    797,
    1072,
    454,
    1131,
    872,
    655,
    351,
    403,
    533,
    655,
    407,
    560,
    499,
    507,
    622,
    450,
    655,
    1147,
    636,
    827,
    634,
    933,
    585,
    688,
    432,
    788,
    884,
    540,
    795,
    716,
    940,
    559,
    524,
    719,
    1025,
    507,
    581,
    625,
    1274,
    866,
    614,
    708,
    685,
    500,
    623,
    743,
    486,
    962,
    694,
    427,
    741,
    653,
    830,
    441,
    752,
    797,
    737,
    500,
    847,
    984,
    570,
    954,
    508,
    499,
    657,
    732,
    792,
    690,
    547,
    684,
    659,
    727,
    711,
    590,
    744,
    424,
    494,
    649,
    339,
    418,
    408,
    413,
    397,
    495,
    615,
    1239,
    643,
    728,
    3377,
    1971,
    308,
    811,
    722,
    1122,
    617,
    894,
    836,
    1008,
    1082,
    1351,
    798,
    1243,
    701,
    1123,
    540,
    1144,
    931,
    631,
    1264,
    836,
    879,
    1028,
    1362,
    1114,
    977,
    1653,
    281,
    413,
    610,
    234,
    380,
    437,
    263,
    593,
    30449,
    4421,
    3643,
    1444,
    1829,
    2357,
    2018,
    2272,
    1670,
    2151,
    1662,
    2582,
    2538,
    2754,
    2484,
    2593,
    2150,
    2671,
    2760,
    1768,
    1871,
    1684,
    1607,
    1443,
    2097,
    1881,
    1041,
    1880,
    2089,
    2318,
    1230,
    2445,
    1476,
    1805,
    2203,
    1517,
    2051,
    2494,
    1656,
    2372,
    2204,
    1785,
    2119,
    1413,
    1152,
    2051,
    1714,
    2008,
    1935,
    2175,
    974,
    2233,
    595,
    697,
    4996,
    6354,
    1359,
    1462,
    1402,
    1716,
    2095,
    2584,
    2650,
    2623,
    2019,
    3043,
    2775,
    1554,
    2358,
    3068,
    527,
    752,
    583,
    451,
    674,
    714,
    616,
    896,
    846,
    847,
    558,
    803,
    444,
    658,
    642,
    479,
    751,
    587,
    796,
    664,
    619,
    538,
    693,
    647,
    511,
    488,
    440,
    1359,
    475,
    721,
    1189,
    568,
    309,
    463,
    759,
    448,
    529,
    388,
    488,
    301,
    553,
    416,
    606,
    1305,
    684,
    464,
    607,
    797,
    556,
    549,
    678,
    523,
    690,
    356,
    568,
    599,
    562,
    727,
    638,
    633,
    377,
    1066,
    556,
    486,
    549,
    463,
    620,
    718,
    563,
    1000,
    1008,
    595,
    378,
    462,
    370,
    5117,
    6066,
    2102,
    1603,
    1531,
    1719,
    2673,
    1648,
    3688,
    2790,
    2684,
    2050,
    1759,
    3234,
    2455,
    1483,
    529,
    409,
    439,
    510,
    436,
    335,
    464,
    624,
    656,
    578,
    591,
    306,
    431,
    295,
    635,
    562,
    552,
    306,
    420,
    576,
    557,
    730,
    586,
    598,
    661,
    718,
    626,
    676,
    520,
    542,
    1130,
    589,
    534,
    790,
    427,
    988,
    244,
    376,
    651,
    904,
    516,
    679,
    853,
    670,
    689,
    1217,
    394,
    582,
    670,
    533,
    367,
    1072,
    533,
    321,
    460,
    472,
    424,
    533,
    258,
    629,
    456,
    636,
    420,
    589,
    757,
    594,
    484,
    476,
    553,
    887,
    453,
    373,
    535,
    555,
    418,
    4636,
    1549,
    1754,
    19228,
    3907,
    4038,
    5907,
    3773,
    2968,
    3644,
    3093,
    3038,
    2524,
    3358,
    4715,
    2551,
    2680,
    2579,
    1829,
    1426,
    1427,
    1078,
    839,
    1161,
    1912,
    261,
    296,
    369,
    1834,
    917,
    1840,
    1890,
    1604,
    1520,
    2198,
    1651,
    1481,
    1771,
    1417,
    1832,
    2261,
    2158,
    1769,
    1618,
    1850,
    1794,
    1115,
    2370,
    2131,
    3769,
    348,
    405,
    364,
    375,
    419,
    449,
    405,
    507,
    450,
    409,
    409,
    819,
    515,
    480,
    484,
    346,
    316,
    446,
    458,
    457,
    339,
    406,
    338,
    361,
    646,
    592,
    406,
    290,
    712,
    347,
    466,
    399,
    469,
    457,
    791,
    527,
    371,
    298,
    728,
    299,
    495,
    231,
    401,
    326,
    261,
    597,
    390,
    531,
    437,
    460,
    389,
    389,
    498,
    388,
    1060,
    624,
    702,
    689,
    359,
    407,
    377,
    583,
    629,
    538,
    541,
    634,
    445,
    664,
    741,
    21149,
    6051,
    7699,
    1329,
    596,
    987,
    539,
    1166,
    621,
    888,
    800,
    1148,
    842,
    806,
    726,
    1004,
    1086,
    894,
    783,
    854,
    1086,
    2707,
    1160,
    664,
    1481,
    13219,
    325,
    7290,
    6402,
    1615,
    2910,
    1789,
    1452,
    2240,
    1266,
    1185,
    1427,
    1695,
    4743,
    2351,
    1528,
    1624,
    2763,
    966,
    955,
    855,
    747,
    590,
    979,
    484,
    721,
    491,
    572,
    314,
    987,
    919,
    394,
    541,
    941,
    425,
    1183,
    1046,
    678,
    597,
    572,
    478,
    411,
    509,
    354,
    494,
    482,
    508,
    641,
    1013,
    614,
    716,
    789,
    423,
    588,
    603,
    792,
    957,
    431,
    584,
    419,
    273,
    468,
    427,
    429,
    802,
    386,
    651,
    420,
    553,
    410,
    442,
    680,
    412,
    549,
    708,
    465,
    1135,
    686,
    562,
    410,
    802,
    406,
    422,
    461,
    664,
    660,
    1103,
    544,
    590,
    555,
    768,
    692,
    939,
    8114,
    1090,
    1294,
    1132,
    1365,
    531,
    631,
    475,
    592,
    1202,
    1161,
    1126,
    358,
    1067,
    721,
    658,
    463,
    641,
    916,
    600,
    765,
    767,
    1800,
    1094,
    543,
    535,
    1483,
    1423,
    711,
    1211,
    1517,
    1127,
    806,
    996,
    1961,
    1626,
    2202,
    1783,
    2155,
    1303,
    1462,
    1078,
    652,
    815,
    11701,
    19502,
    5683,
    1377,
    1281,
    1604,
    1307,
    1048,
    1392,
    1262,
    1236,
    1695,
    1710,
    1706,
    2107,
    1836,
    1103,
    2971,
    600,
    1210,
    1369,
    1974,
    1111,
    892,
    1427,
    2103,
    6135,
    306,
    504,
    436,
    397,
    434,
    4787,
    3857,
    19492,
    2855,
    2055,
    1768,
    2789,
    1187,
    928,
    907,
    1051,
    1043,
    967,
    1184,
    1845,
    1103,
    1049,
    1669,
    1394,
    1670,
    1396,
    1373,
    2454,
    2748,
    3452,
    2477,
    2229,
    1977,
    7688,
    477,
    449,
    394,
    389,
    371,
    365,
    442,
    8441,
    21778,
    10805,
    2183,
    3948,
    809,
    2045,
    1158,
    1513,
    1142,
    964,
    2177,
    1054,
    2803,
    1127,
    1205,
    1139,
    3039,
    1513,
    734,
    5536,
    1425,
    955,
    869,
    2456
  ],
  "frame_rasterizer_times": [
    6171,
    4008,
    2807,
    4150,
    2908,
    3534,
    5410,
    4087,
    6124,
    6655,
    3314,
    4314,
    2972,
    3180,
    3463,
    2886,
    3260,
    2612,
    4290,
    3231,
    3050,
    3275,
    2537,
    2770,
    3845,
    2425,
    3068,
    2678,
    2741,
    3002,
    3551,
    2231,
    3078,
    2303,
    2556,
    3683,
    4424,
    2405,
    3234,
    2185,
    3265,
    3204,
    2934,
    3146,
    2661,
    3453,
    3091,
    2374,
    4022,
    2538,
    3367,
    2326,
    3144,
    2175,
    3185,
    3266,
    4053,
    3324,
    3135,
    3392,
    3081,
    3150,
    3145,
    3053,
    3062,
    3362,
    3052,
    2984,
    3728,
    3183,
    2183,
    3015,
    3442,
    2942,
    3402,
    2560,
    2539,
    3691,
    2265,
    2550,
    3184,
    3221,
    3910,
    2880,
    2828,
    2266,
    3355,
    2918,
    2565,
    3059,
    2732,
    3663,
    3613,
    3341,
    2799,
    3303,
    3305,
    3562,
    3016,
    3057,
    3863,
    5341,
    2407,
    5039,
    3240,
    3096,
    2488,
    2318,
    3622,
    3313,
    3259,
    2864,
    3689,
    3262,
    3256,
    2445,
    2843,
    3437,
    2567,
    2164,
    3454,
    3506,
    3544,
    3196,
    3160,
    2962,
    3875,
    2705,
    3232,
    3126,
    2989,
    3842,
    3188,
    3310,
    2814,
    3784,
    3106,
    2649,
    4805,
    3433,
    3447,
    3485,
    2299,
    2757,
    2850,
    3681,
    3475,
    3521,
    3095,
    3065,
    4501,
    3417,
    2471,
    4338,
    2993,
    3655,
    3167,
    3570,
    3746,
    3452,
    2936,
    3104,
    2976,
    2615,
    3888,
    2832,
    2212,
    3483,
    3566,
    2605,
    2814,
    2685,
    2447,
    2499,
    2363,
    2227,
    3120,
    3048,
    3451,
    2633,
    3413,
    3632,
    3394,
    3336,
    3208,
    3598,
    2571,
    3259,
    3106,
    8740,
    2324,
    3690,
    3460,
    3255,
    4144,
    3303,
    3268,
    3402,
    2624,
    2467,
    2921,
    3515,
    3067,
    3480,
    3025,
    3144,
    3154,
    6222,
    3259,
    3544,
    1958,
    2584,
    2502,
    2157,
    3910,
    2768,
    2496,
    2777,
    2408,
    3348,
    3112,
    2755,
    2336,
    2313,
    2322,
    2286,
    2731,
    2873,
    2616,
    2294,
    2546,
    2730,
    2510,
    1981,
    2554,
    2498,
    3450,
    3202,
    2477,
    3375,
    3250,
    3112,
    2360,
    2141,
    2709,
    2728,
    3603,
    2943,
    2506,
    2749,
    3263,
    3297,
    3280,
    2881,
    3138,
    2076,
    2106,
    2238,
    3578,
    2610,
    3445,
    3294,
    2518,
    3813,
    3159,
    3381,
    2466,
    2928,
    2753,
    3087,
    3219,
    3316,
    8224,
    4574,
    5316,
    5558,
    4211,
    5819,
    4512,
    4387,
    5538,
    5442,
    5462,
    4372,
    4950,
    4817,
    4436,
    2443,
    2471,
    2494,
    3121,
    3014,
    3414,
    3095,
    3745,
    3298,
    2603,
    3119,
    2211,
    3020,
    3146,
    3026,
    3392,
    3078,
    3327,
    3210,
    3072,
    2163,
    3124,
    3040,
    3616,
    3248,
    2068,
    2913,
    3272,
    2421,
    2341,
    3322,
    3412,
    2660,
    1440,
    2325,
    2736,
    2590,
    3490,
    3023,
    1410,
    3515,
    3229,
    3089,
    2597,
    2960,
    3058,
    3543,
    3352,
    3391,
    2990,
    3141,
    3196,
    3680,
    3011,
    3306,
    3551,
    3302,
    2128,
    3307,
    3203,
    3575,
    3329,
    3335,
    3027,
    3320,
    3388,
    3332,
    3104,
    3873,
    2898,
    3161,
    4280,
    2946,
    3858,
    2973,
    2479,
    3565,
    2316,
    2343,
    1508,
    1657,
    2002,
    1881,
    2589,
    2553,
    2093,
    2175,
    2462,
    2987,
    3053,
    2527,
    3919,
    2516,
    2790,
    3895,
    2983,
    2786,
    3784,
    3407,
    3425,
    3598,
    3411,
    3522,
    3837,
    3837,
    2948,
    3494,
    3445,
    4029,
    2528,
    3885,
    2662,
    2949,
    2247,
    3547,
    2369,
    4008,
    4077,
    1771,
    2246,
    1905,
    2052,
    2377,
    2708,
    4479,
    2866,
    2009,
    2777,
    1957,
    2446,
    1912,
    2346,
    2411,
    2643,
    1968,
    3147,
    3421,
    3042,
    3292,
    3994,
    3537,
    3385,
    3631,
    3455,
    2494,
    2136,
    1976,
    2012,
    2506,
    2896,
    3110,
    2335,
    3190,
    3485,
    2490,
    3341,
    2844,
    2657,
    3266,
    2027,
    2107,
    4108,
    2577,
    3726,
    2754,
    2434,
    2447,
    2268,
    1755,
    2680,
    1919,
    2003,
    1806,
    2363,
    2602,
    1798,
    1857,
    2530,
    2868,
    3148,
    3289,
    2465,
    3402,
    2850,
    2986,
    2509,
    2303,
    1680,
    5711,
    1984,
    1239,
    1144,
    1383,
    1741,
    2176,
    1872,
    1997,
    2240,
    1905,
    2974,
    2684,
    1770,
    1493,
    1360,
    1603,
    2565,
    1707,
    2454,
    2158,
    2005,
    2148,
    2664,
    2884,
    2318,
    1944,
    1993,
    1965,
    2024,
    2662,
    2420,
    2597,
    2422,
    2145,
    2082,
    1398,
    1690,
    1600,
    1927,
    1989,
    1912,
    2301,
    1558,
    2206,
    2718,
    2259,
    1840,
    2135,
    2295,
    1736,
    1791,
    1911,
    1953,
    2349,
    2079,
    2058,
    3274,
    2903,
    2714,
    1752,
    2463,
    1863,
    1792,
    2596,
    2368,
    1837,
    2084,
    2761,
    2651,
    2604,
    2491,
    1693,
    2567,
    2078,
    3668,
    2361,
    2033,
    2603,
    2443,
    2027,
    3329,
    2547,
    2588,
    1999,
    2559,
    2845,
    1803,
    2020,
    2282,
    2110,
    1917,
    2814,
    2103,
    2277,
    2481,
    2772,
    2021,
    2048,
    1541,
    1628,
    2406,
    2300,
    2700,
    3129,
    2493,
    1269,
    1529,
    2257,
    1504,
    2284,
    2372,
    2113,
    1377,
    1674,
    2821,
    2772,
    3519,
    2039,
    2177,
    2097,
    1665,
    1791,
    1895,
    4252,
    1740,
    2516,
    1782,
    2514,
    2470,
    1795,
    2059,
    2650,
    2213,
    2604,
    2337,
    1877,
    2784,
    1824,
    2878,
    2679,
    2574,
    2538,
    2255,
    2627,
    2745,
    3503,
    2363,
    3186,
    3210,
    2918,
    2903,
    3608,
    2442,
    2393,
    3869,
    9676,
    4013,
    2594,
    4176,
    3271,
    4212,
    3758,
    2625,
    3237,
    3291,
    4032,
    3710,
    4734,
    3534,
    3784,
    3822,
    2540,
    3994,
    4348,
    2803,
    2583,
    4532,
    4840,
    4267,
    4338,
    3069,
    4158,
    3115,
    3407,
    3222,
    4439,
    3693,
    3962,
    4024,
    2858,
    3219,
    2872,
    3802,
    5993,
    2778,
    3720,
    3638,
    3749,
    3310,
    3950,
    3796,
    3742,
    3971,
    3041,
    3715,
    2863,
    4040,
    3581,
    5013,
    5528,
    2958,
    7238,
    6504,
    8631,
    8560,
    9703,
    8106,
    5366,
    8116,
    6025,
    6543,
    5299,
    5885,
    4289,
    2945,
    3020,
    2524,
    3642,
    3994,
    3902,
    3847,
    2977,
    3961,
    3784,
    3891,
    3984,
    3727,
    3164,
    3630,
    3403,
    3285,
    3373,
    4117,
    3707,
    3794,
    3667,
    3695,
    2631,
    3742,
    3842,
    2669,
    4127,
    3800,
    3714,
    3625,
    3732,
    2506,
    2687,
    2670,
    3220,
    3414,
    3079,
    3568,
    2899,
    4064,
    2838,
    5336,
    3483,
    2643,
    3980,
    3626,
    3644,
    3549,
    4259,
    3934,
    3045,
    4049,
    3771,
    3846,
    3746,
    3740,
    3879,
    3757,
    3746,
    3379,
    4734,
    4194,
    3787,
    3674,
    4328,
    3786,
    4226,
    3776,
    3917,
    3875,
    2512,
    3592,
    3765,
    2759,
    4677,
    10295,
    5373,
    3465,
    5944,
    4139,
    5547,
    5200,
    4081,
    5900,
    3027,
    6390,
    5892,
    4335,
    2990,
    4000,
    3890,
    3754,
    3918,
    2367,
    2843,
    2578,
    3252,
    3688,
    4291,
    3715,
    3893,
    2798,
    4260,
    2927,
    5320,
    4666,
    3499,
    3544,
    3941,
    3423,
    3121,
    3848,
    3840,
    3138,
    3169,
    3330,
    3899,
    3966,
    3916,
    4098,
    2542,
    3161,
    3598,
    3679,
    2694,
    4128,
    3644,
    3672,
    3880,
    3843,
    3292,
    4079,
    3105,
    2924,
    3229,
    3819,
    3741,
    3535,
    3622,
    2503,
    3954,
    2668,
    2485,
    3894,
    2780,
    4226,
    3532,
    3915,
    4103,
    2554,
    3641,
    3898,
    3954,
    4141,
    3778,
    4053,
    3898,
    3941,
    2869,
    4388,
    4169,
    3304,
    2800,
    4047,
    3094,
    4873,
    4006,
    2159,
    20659,
    6988,
    5909,
    7198,
    5249,
    11435,
    5664,
    5813,
    8750,
    6415,
    8083,
    6340,
    3698,
    3155,
    2732,
    2714,
    2881,
    2185,
    2077,
    3082,
    3368,
    2434,
    4088,
    2657,
    2498,
    7758,
    3757,
    2146,
    2179,
    3851,
    3691,
    3318,
    3775,
    3871,
    2285,
    3245,
    3021,
    3414,
    2368,
    3622,
    3094,
    3177,
    3477,
    2725,
    2826,
    3912,
    3420,
    2192,
    3494,
    3435,
    3298,
    3408,
    3402,
    2878,
    3377,
    3348,
    3836,
    2865,
    3287,
    3243,
    3847,
    3618,
    2656,
    3239,
    3282,
    3293,
    2431,
    3329,
    3632,
    3703,
    3520,
    3356,
    2648,
    3042,
    3191,
    3400,
    3444,
    2507,
    4209,
    2693,
    3987,
    3599,
    3480,
    3345,
    2355,
    3612,
    3424,
    3831,
    2244,
    2841,
    3734,
    2915,
    3774,
    3283,
    2868,
    3332,
    3486,
    3496,
    3993,
    3582,
    3572,
    2900,
    2597,
    3875,
    3411,
    3349,
    3647,
    2966,
    3368,
    3412,
    3354,
    3520,
    2309,
    3266,
    4765,
    3463,
    4720,
    2551,
    2541,
    1494,
    1975,
    1685,
    2198,
    3377,
    1879,
    2623,
    2590,
    2791,
    2515,
    2664,
    2074,
    1687,
    2813,
    2571,
    2457,
    3361,
    2326,
    3117,
    3204,
    2205,
    3283,
    38174,
    5476,
    5298,
    8547,
    5202,
    5771,
    6236,
    6125,
    6850,
    5062,
    7250,
    6789,
    6159,
    5242,
    4414,
    6281,
    4325,
    2773,
    3847,
    3910,
    3665,
    3213,
    3897,
    4100,
    3729,
    3277,
    3459,
    3308,
    2853,
    3516,
    3455,
    3508,
    2585,
    3611,
    3334,
    6528,
    11462,
    3564,
    3633,
    3992,
    3513,
    2503,
    4105,
    3399,
    3417,
    3578,
    2738,
    3974,
    4760,
    3355,
    3230,
    3648,
    3642,
    3425,
    3865,
    3075,
    3295,
    3255,
    3514,
    4414,
    2423,
    4093,
    3747,
    3456,
    3913,
    3454,
    3618,
    3591,
    3538,
    3504,
    3073,
    3901,
    3005,
    2405,
    2365,
    2834,
    2541,
    3819,
    2961,
    3771,
    3208,
    2850,
    3042,
    3238,
    3059,
    2608,
    3840,
    2770,
    3409,
    3458,
    3830,
    2632,
    3718,
    3368,
    1683,
    2480,
    2358,
    1602,
    1333,
    1606,
    1363,
    1428,
    1050,
    1782,
    3487,
    1346,
    1390,
    1077,
    1464,
    1452,
    1538,
    2036,
    1646,
    1917,
    2098,
    1822,
    1793,
    1902,
    1852,
    2154,
    2806,
    2251,
    1863,
    2337,
    3549,
    3148,
    3435,
    3164,
    2344,
    3292,
    4397,
    2977,
    3337,
    2043,
    2752,
    3666,
    3202,
    3095,
    2859,
    1917,
    3878,
    3076,
    2756,
    2435,
    2307,
    3312,
    2417,
    2369,
    2481,
    2154,
    2369,
    1887,
    2976,
    1978,
    2976,
    2741,
    8233,
    1773,
    2631,
    2738,
    3584,
    2350,
    2896,
    3703,
    3420,
    2952,
    2974,
    2948,
    2158,
    3733,
    3861,
    1633,
    2231,
    2401,
    3395,
    2174,
    2294,
    1808,
    1850,
    2389,
    2693,
    2608,
    2368,
    3208,
    2198,
    1896,
    2565,
    1966,
    2114,
    2313,
    2221,
    2094,
    2234,
    3532,
    2504,
    2783,
    2408,
    8115,
    2487,
    3620,
    2361,
    2812,
    3374,
    3749,
    2650,
    6884,
    4983,
    4047,
    2449,
    2672,
    1792,
    3792,
    3293,
    1882,
    2791,
    2689,
    3512,
    2327,
    2311,
    2133,
    2236,
    2166,
    2363,
    1672,
    1496,
    2262,
    3073,
    1989,
    2276,
    3511
  ],
  "new_gen_gc_count": 68,
  "old_gen_gc_count": 6
}