{
  "average_frame_build_time_millis": 1.138,
  "90th_percentile_frame_build_time_millis": 2.297,
  "99th_percentile_frame_build_time_millis": 6.478,
  "worst_frame_build_time_millis": 19.245,
  "missed_frame_build_budget_count": 2,
  "average_frame_rasterizer_time_millis": 3.311,
  "90th_percentile_frame_rasterizer_time_millis": 4.372,
  "99th_percentile_frame_rasterizer_time_millis": 7.67,
  "worst_frame_rasterizer_time_millis": 15.735,
  "average_layer_cache_count": 0.0,
  "90th_percentile_layer_cache_count": 0,
  "99th_percentile_layer_cache_count": 0,
  "worst_layer_cache_count": 0,
  "average_layer_cache_memory": 0.0,
  "90th_percentile_layer_cache_memory": 0.0,
  "99th_percentile_layer_cache_memory": 0.0,
  "worst_layer_cache_memory": 0.0,
  "average_picture_cache_count": 0.0,
  "90th_percentile_picture_cache_count": 0,
  "99th_percentile_picture_cache_count": 0,
  "worst_picture_cache_count": 0,
  "average_picture_cache_memory": 0.0,
  "90th_percentile_picture_cache_memory": 0.0,
  "99th_percentile_picture_cache_memory": 0.0,
  "worst_picture_cache_memory": 0.0,
  "missed_frame_rasterizer_budget_count": 0,
  "frame_count": 856,
  "frame_build_times": [
    6478,
    4992,
    1670,
    2235,
    1258,
    1986,
    1777,
    1762,
    1404,
    2419,
    1498,
    2297,
    1620,
    329,
    674,
    309,
    457,
    288,
    510,
    390,
    648,
    450,
    506,
    809,
    560,
    558,
    637,
    547,
    595,
    423,
    195,
    344,
    379,
    418,
    455,
    488,
    641,
    1217,
    272,
    353,
    402,
    342,
    538,
    742,
    656,
    459,
    537,
    713,
    522,
    697,
    596,
    603,
    1005,
    482,
    561,
    555,
    901,
    531,
    374,
    374,
    483,
    370,
    565,
    558,
    609,
    522,
    520,
    596,
    431,
    525,
    502,
    427,
    573,
    434,
    433,
    593,
    511,
    578,
    227,
    357,
    350,
    550,
    537,
    544,
    532,
    672,
    703,
    439,
    503,
    856,
    255,
    371,
    452,
    415,
    614,
    415,
    405,
    277,
    273,
    402,
    338,
    333,
    450,
    488,
    527,
    655,
    462,
    382,
    635,
    270,
    404,
    668,
    279,
    582,
    684,
    531,
    378,
    379,
    573,
    559,
    457,
    340,
    439,
    821,
    417,
    410,
    392,
    244,
    243,
    397,
    497,
    500,
    392,
    532,
    1661,
    317,
    476,
    546,
    281,
    866,
    284,
    473,
    466,
    357,
    743,
    409,
    294,
    407,
    320,
    1642,
    533,
    1019,
    1229,
    533,
    448,
    270,
    289,
    350,
    355,
    335,
    652,
    559,
    527,
    533,
    422,
    574,
    402,
    257,
    293,
    665,
    457,
    562,
    526,
    613,
    1192,
    1031,
    320,
    449,
    295,
    734,
    429,
    434,
    482,
    522,
    520,
    357,
    1360,
    751,
    488,
    859,
    472,
    471,
    1075,
    555,
    602,
    350,
    285,
    288,
    470,
    466,
    440,
    449,
    535,
    726,
    720,
    769,
    557,
    727,
    328,
    654,
    400,
    793,
    403,
    473,
    304,
    548,
    569,
    296,
    410,
    556,
    378,
    199,
    532,
    289,
    532,
    269,
    266,
    287,
    330,
    543,
    672,
    540,
    863,
    531,
    625,
    507,
    441,
    605,
    458,
    975,
    369,
    953,
    362,
    1122,
    557,
    2644,
    513,
    542,
    475,
    568,
    419,
    672,
    785,
    655,
    532,
    509,
    612,
    487,
    233,
    997,
    947,
    244,
    293,
    440,
    437,
    447,
    538,
    534,
    438,
    12006,
    9380,
    2780,
    2901,
    2691,
    2359,
    2489,
    4015,
    5770,
    1380,
    1830,
    2524,
    1561,
    2812,
    352,
    438,
    397,
    494,
    397,
    676,
    451,
    300,
    415,
    854,
    334,
    631,
    550,
    497,
    403,
    246,
    416,
    478,
    572,
    821,
    571,
    595,
    437,
    423,
    504,
    527,
    964,
    1067,
    524,
    404,
    624,
    732,
    297,
    516,
    429,
    538,
    578,
    897,
    535,
    1104,
    364,
    595,
    587,
    452,
    438,
    593,
    596,
    1122,
    656,
    573,
    435,
    378,
    575,
    936,
    567,
    480,
    569,
    483,
    519,
    545,
    458,
    1224,
    402,
    579,
    405,
    719,
    1118,
    871,
    435,
    688,
    560,
    534,
    514,
    413,
    640,
    663,
    454,
    5107,
    2002,
    1142,
    2453,
    2018,
    1365,
    1084,
    1353,
    1120,
    1733,
    1412,
    461,
    338,
    361,
    849,
    965,
    1194,
    1127,
    1095,
    1187,
    960,
    907,
    1429,
    1203,
    1531,
    1532,
    2034,
    2345,
    2063,
    2053,
    2097,
    1940,
    2390,
    2505,
    2991,
    2636,
    2520,
    2349,
    2104,
    2033,
    1938,
    1111,
    1301,
    2306,
    1179,
    2392,
    2214,
    1514,
    2799,
    2359,
    1092,
    2009,
    2614,
    2371,
    2572,
    2283,
    2298,
    2457,
    2179,
    2129,
    2751,
    2203,
    1660,
    1930,
    1785,
    1639,
    1572,
    1743,
    1343,
    992,
    1922,
    1799,
    1280,
    1282,
    1636,
    1343,
    736,
    642,
    1739,
    1748,
    2255,
    2292,
    2285,
    2206,
    2121,
    2162,
    2512,
    1475,
    2275,
    1735,
    2265,
    1116,
    1349,
    1215,
    1328,
    1869,
    700,
    1819,
    666,
    1464,
    934,
    949,
    787,
    738,
    853,
    871,
    1056,
    1838,
    3032,
    1570,
    1650,
    2197,
    2270,
    1614,
    1946,
    1735,
    1791,
    8976,
    4085,
    3928,
    530,
    1269,
    895,
    786,
    620,
    844,
    844,
    878,
    757,
    232,
    824,
    788,
    886,
    685,
    929,
    4592,
    763,
    792,
    1015,
    925,
    945,
    1254,
    784,
    889,
    930,
    881,
    1986,
    814,
    555,
    852,
    693,
    812,
    691,
    584,
    727,
    645,
    722,
    681,
    479,
    468,
    774,
    462,
    781,
    492,
    2532,
    900,
    692,
    698,
    540,
    507,
    581,
    579,
    564,
    698,
    525,
    454,
    700,
    483,
    689,
    614,
    481,
    449,
    396,
    556,
    449,
    732,
    449,
    632,
    945,
    596,
    640,
    564,
    905,
    506,
    543,
    428,
    799,
    390,
    10213,
    6190,
    499,
    890,
    657,
    548,
    907,
    776,
    699,
    744,
    837,
    1021,
    580,
    1006,
    1280,
    667,
    615,
    540,
    815,
    605,
    574,
    624,
    674,
    1414,
    582,
    1187,
    896,
    1645,
    234,
    470,
    430,
    15161,
    1832,
    1956,
    1406,
    1219,
    1179,
    1606,
    1528,
    1845,
    2211,
    2106,
    2602,
    1891,
    2055,
    3030,
    2811,
    3051,
    2225,
    2887,
    2889,
    2720,
    2887,
    3328,
    972,
    1490,
    1766,
    2016,
    1512,
    1808,
    1827,
    1685,
    1926,
    1506,
    1919,
    2116,
    2153,
    2059,
    1891,
    2030,
    2148,
    1697,
    1044,
    2173,
    1713,
    2239,
    1536,
    1646,
    1781,
    1456,
    2063,
    1602,
    1571,
    4190,
    817,
    1982,
    2467,
    491,
    608,
    488,
    17590,
    5563,
    1906,
    1734,
    1495,
    1648,
    1848,
    2545,
    2434,
    1480,
    1454,
    1262,
    2811,
    2057,
    1767,
    558,
    392,
    459,
    679,
    616,
    489,
    569,
    472,
    1286,
    624,
    699,
    957,
    700,
    496,
    554,
    545,
    554,
    444,
    687,
    594,
    721,
    456,
    564,
    532,
    374,
    401,
    438,
    539,
    588,
    283,
    803,
    459,
    541,
    570,
    560,
    528,
    563,
    726,
    766,
    581,
    412,
    434,
    372,
    526,
    1111,
    1013,
    761,
    601,
    772,
    546,
    475,
    489,
    469,
    539,
    662,
    614,
    465,
    425,
    483,
    460,
    276,
    392,
    501,
    724,
    490,
    444,
    590,
    1002,
    594,
    575,
    472,
    527,
    304,
    682,
    435,
    1386,
    12843,
    8234,
    2332,
    1159,
    2109,
    2342,
    1878,
    3548,
    3258,
    2990,
    2555,
    3652,
    1637,
    1803,
    409,
    556,
    388,
    422,
    431,
    574,
    389,
    725,
    691,
    396,
    390,
    280,
    679,
    571,
    432,
    436,
    539,
    535,
    702,
    621,
    450,
    648,
    553,
    593,
    435,
    704,
    584,
    457,
    748,
    641,
    477,
    955,
    574,
    1071,
    292,
    531,
    551,
    581,
    674,
    479,
    442,
    434,
    490,
    345,
    330,
    379,
    478,
    717,
    509,
    516,
    600,
    778,
    623,
    518,
    595,
    708,
    595,
    532,
    419,
    502,
    501,
    631,
    456,
    572,
    682,
    438,
    539,
    459,
    359,
    567,
    800,
    520,
    497,
    423,
    310,
    325,
    3345,
    1738,
    999,
    19245,
    2711,
    2443,
    2452,
    2746,
    2806,
    2237,
    3383,
    2372,
    2821,
    3933,
    5016,
    3952,
    2866,
    1987,
    2746,
    2722,
    1295,
    1214,
    1557,
    2258,
    439,
    424,
    376
  ],
  "frame_rasterizer_times": [
    7894,
    6871,
    4533,
    3940,
    4365,
    4106,
    3716,
    4448,
    4094,
    5139,
    3472,
    5521,
    2804,
    2395,
    3073,
    2440,
    3926,
    2369,
    3668,
    2507,
    2314,
    2420,
    3081,
    2745,
    3744,
    3607,
    2196,
    3578,
    2311,
    1906,
    3060,
    2853,
    2957,
    3640,
    3078,
    3100,
    3649,
    2951,
    2599,
    2274,
    2464,
    2439,
    2766,
    2273,
    2307,
    3398,
    3163,
    3870,
    2341,
    2287,
    3168,
    3188,
    3664,
    3273,
    2324,
    3493,
    3450,
    4186,
    2494,
    2764,
    3403,
    2928,
    3519,
    3452,
    2282,
    3229,
    2306,
    3769,
    2550,
    3307,
    3108,
    3535,
    2315,
    3278,
    3525,
    3632,
    3535,
    3971,
    2134,
    3116,
    2200,
    2277,
    3001,
    3071,
    3061,
    2335,
    3215,
    3376,
    3181,
    3136,
    2720,
    3355,
    3299,
    2203,
    3433,
    3215,
    2176,
    2219,
    2024,
    2516,
    2493,
    3328,
    2559,
    2171,
    2329,
    2420,
    2796,
    2591,
    2703,
    2735,
    2709,
    4083,
    2636,
    3629,
    3797,
    2427,
    3125,
    2273,
    2424,
    2999,
    2860,
    3080,
    4222,
    2297,
    2969,
    3823,
    2887,
    2386,
    3404,
    3186,
    3332,
    3173,
    2771,
    2528,
    3245,
    2452,
    3232,
    2490,
    2191,
    2869,
    2238,
    3013,
    3533,
    3269,
    2930,
    3008,
    3132,
    3468,
    2912,
    3162,
    3050,
    3579,
    3627,
    3424,
    4176,
    2745,
    2393,
    2619,
    3507,
    2992,
    3112,
    3288,
    3225,
    2948,
    3030,
    3247,
    2779,
    3220,
    2286,
    2850,
    2808,
    2964,
    2879,
    2354,
    3881,
    3274,
    3335,
    3129,
    2253,
    2331,
    2637,
    3327,
    2716,
    3112,
    3247,
    3537,
    3530,
    3460,
    2707,
    3309,
    3734,
    3061,
    2843,
    3096,
    4161,
    2260,
    3065,
    2341,
    3872,
    3515,
    2310,
    4024,
    3588,
    3399,
    2925,
    4029,
    3253,
    3284,
    3396,
    2962,
    2714,
    2616,
    2720,
    2934,
    3137,
    2478,
    2280,
    2412,
    2397,
    2301,
    2609,
    2475,
    2730,
    2028,
    2068,
    2273,
    2122,
    1985,
    2763,
    3230,
    3976,
    2323,
    3501,
    3297,
    3449,
    3059,
    3046,
    2305,
    3333,
    3705,
    2312,
    3231,
    2989,
    3674,
    2818,
    3915,
    2998,
    3011,
    3126,
    2713,
    2875,
    3507,
    4313,
    2338,
    3312,
    2388,
    2840,
    3061,
    2169,
    3765,
    3203,
    3285,
    3346,
    3023,
    3031,
    3359,
    2140,
    2195,
    2520,
    3233,
    6270,
    7119,
    6962,
    4408,
    6163,
    8367,
    5074,
    6622,
    4743,
    7579,
    7132,
    4453,
    3555,
    3005,
    3134,
    3250,
    3275,
    3446,
    3196,
    3432,
    2218,
    2367,
    3666,
    3639,
    3553,
    4386,
    3107,
    3374,
    2460,
    2488,
    3240,
    2580,
    2781,
    3039,
    3270,
    3477,
    3513,
    3718,
    4203,
    3667,
    4187,
    3506,
    3643,
    3349,
    2881,
    2693,
    4139,
    3794,
    2268,
    3482,
    3364,
    2318,
    2956,
    3134,
    3379,
    3389,
    3332,
    3174,
    2136,
    2307,
    3821,
    3210,
    3636,
    3301,
    3145,
    3059,
    2900,
    4524,
    3591,
    3686,
    3060,
    3908,
    2700,
    3597,
    3241,
    2861,
    3530,
    3369,
    2304,
    3621,
    3155,
    3265,
    3182,
    3144,
    2220,
    2244,
    3077,
    2428,
    3289,
    3259,
    5804,
    1500,
    2099,
    2379,
    1822,
    2318,
    2250,
    1772,
    2238,
    2581,
    1871,
    3088,
    1656,
    1572,
    1523,
    1893,
    2200,
    2590,
    2253,
    2525,
    3447,
    2057,
    2214,
    2276,
    2321,
    2805,
    3121,
    2780,
    2390,
    3363,
    3371,
    3436,
    3511,
    3726,
    3889,
    3538,
    3780,
    3848,
    3613,
    3654,
    3365,
    2005,
    3793,
    4037,
    3150,
    4179,
    4696,
    2857,
    3050,
    3038,
    2371,
    3539,
    3675,
    4011,
    2670,
    3816,
    2933,
    3301,
    3448,
    3401,
    3422,
    3149,
    3570,
    3979,
    3464,
    3750,
    2874,
    3784,
    2762,
    2446,
    4105,
    2233,
    2283,
    2319,
    3342,
    2136,
    2199,
    3313,
    3095,
    3294,
    3419,
    3371,
    3254,
    3131,
    3319,
    4024,
    2173,
    2612,
    2652,
    3414,
    2561,
    2367,
    2181,
    2559,
    1696,
    1708,
    1506,
    1636,
    1424,
    1619,
    1949,
    1871,
    2165,
    2085,
    1988,
    2037,
    2925,
    3499,
    4227,
    3593,
    3557,
    2263,
    3391,
    3329,
    3207,
    3199,
    2322,
    5804,
    3246,
    1146,
    645,
    1503,
    2229,
    1940,
    1943,
    2630,
    2351,
    2602,
    1690,
    2420,
    2623,
    1703,
    2512,
    1526,
    2618,
    2866,
    2646,
    3234,
    2712,
    2393,
    2574,
    2963,
    2638,
    2631,
    1720,
    2477,
    1755,
    2630,
    1770,
    2506,
    3301,
    1811,
    2622,
    2781,
    2507,
    2080,
    2558,
    2706,
    2169,
    1829,
    2514,
    2301,
    2277,
    2291,
    3052,
    2248,
    1710,
    2225,
    3020,
    1731,
    1806,
    1939,
    2043,
    1445,
    1698,
    1728,
    1879,
    1904,
    2655,
    1629,
    1957,
    1526,
    2107,
    1874,
    2477,
    2614,
    1638,
    1853,
    1871,
    3108,
    1650,
    2039,
    2189,
    1816,
    2373,
    1904,
    2138,
    1260,
    2030,
    2179,
    1918,
    1964,
    2260,
    2034,
    1920,
    2387,
    1889,
    1601,
    2746,
    2374,
    2925,
    3058,
    2494,
    2612,
    2890,
    1908,
    2674,
    2045,
    2058,
    2165,
    1759,
    2222,
    1724,
    1824,
    2298,
    2483,
    1992,
    3588,
    2194,
    3646,
    9401,
    4184,
    1814,
    2192,
    2705,
    2559,
    2638,
    2843,
    3342,
    3694,
    3998,
    3354,
    3241,
    4486,
    3698,
    4631,
    4682,
    2419,
    3254,
    3841,
    4400,
    4642,
    2554,
    3123,
    4465,
    3868,
    3054,
    4510,
    4340,
    4492,
    3859,
    3960,
    3827,
    3808,
    4048,
    3812,
    3839,
    3862,
    3910,
    3316,
    2988,
    4129,
    3952,
    3951,
    3342,
    4255,
    3861,
    3702,
    3740,
    3430,
    4809,
    3824,
    2275,
    3951,
    3898,
    3565,
    3585,
    2562,
    8830,
    6791,
    3284,
    6277,
    6713,
    6901,
    6526,
    7670,
    7291,
    7524,
    7469,
    5752,
    6541,
    4423,
    3767,
    3515,
    3425,
    4037,
    3920,
    3810,
    4478,
    4504,
    4243,
    4056,
    3849,
    3830,
    3670,
    3625,
    3851,
    3894,
    3842,
    3861,
    3734,
    3775,
    4747,
    3758,
    3566,
    4714,
    4217,
    4142,
    3418,
    4295,
    4507,
    3737,
    3055,
    3274,
    3885,
    3679,
    3831,
    3733,
    4030,
    3767,
    2742,
    3246,
    2622,
    3724,
    3073,
    2676,
    2611,
    2402,
    2512,
    2449,
    2525,
    4236,
    4077,
    3345,
    3901,
    3952,
    4372,
    4073,
    2863,
    3933,
    3517,
    3788,
    3649,
    3210,
    4541,
    3839,
    3982,
    3816,
    3260,
    3909,
    3941,
    4568,
    4173,
    3156,
    4045,
    2782,
    2660,
    4758,
    4072,
    6086,
    11385,
    4844,
    3954,
    6471,
    4056,
    5379,
    4694,
    3929,
    3421,
    4992,
    3804,
    3153,
    3364,
    4068,
    3980,
    2709,
    3588,
    3084,
    4607,
    2615,
    4007,
    2598,
    4099,
    3161,
    2427,
    3889,
    4067,
    4013,
    4492,
    4066,
    4090,
    2793,
    2632,
    4427,
    2543,
    4470,
    4329,
    2449,
    4067,
    3802,
    4212,
    3735,
    3843,
    3868,
    3392,
    3026,
    4552,
    3714,
    3871,
    3834,
    4460,
    4018,
    3905,
    3815,
    3019,
    3380,
    3006,
    3260,
    2741,
    4138,
    4150,
    4524,
    3914,
    3595,
    3819,
    3603,
    3751,
    3871,
    4281,
    3857,
    4381,
    4106,
    4617,
    4470,
    2653,
    3365,
    3925,
    3719,
    4188,
    3859,
    4067,
    2738,
    4255,
    3207,
    4910,
    4124,
    3716,
    2478,
    2726,
    5130,
    3025,
    3301,
    15735,
    6701,
    5805,
    8256,
    7185,
    13542,
    6397,
    5377,
    6873,
    8068,
    6818,
    5050,
    3356,
    2991,
    4045,
    4166,
    2755,
    3111,
    3115,
    3584,
    3689,
    3690,
    2378,
    3562
  ],
  "new_gen_gc_count": 31,
  "old_gen_gc_count": 2
}